{
    "actions": {
        "Bite.": "Melee Weapon Attack:\n +4 to hit, reach 5 ft., one creature. \nHit:\n 1 piercing damage, and the target must\nsucceed on a DC 10 Constitution saving throw or be poisoned for 1 minute. If the saving throw fails by 5 or more, the target is instead poisoned for 5\n(1d10) minutes and unconscious while poisoned in this way."
    },
    "armor_class": 13,
    "challenge_rating": 0.0,
    "charisma": {
        "modifier": 0,
        "score": 10
    },
    "constitution": {
        "modifier": 0,
        "score": 10
    },
    "description": "Tiny construct, neutral\n",
    "dexterity": {
        "modifier": 0,
        "score": 10
    },
    "features": {
        "Telepathic Bond.": " While the homunculus is on the same plane of existence as its master, it can magically convey what it senses to\nits master, and the two can communicate telepathically. "
    },
    "fly_speed": 40,
    "hit_dice": "2d4",
    "hp_max": 5,
    "intelligence": {
        "modifier": 0,
        "score": 10
    },
    "languages": " understands the languages of its creator but can't speak  ",
    "name": "Homunculus",
    "reactions": {},
    "saving_throws": "Dex +0",
    "senses": " darkvision 60 ft., passive Perception 10  ",
    "skills": "Perception +3, Stealth +4",
    "speed": 20,
    "strength": {
        "modifier": 0,
        "score": 10
    },
    "swim_speed": 0,
    "wisdom": {
        "modifier": 0,
        "score": 10
    }
}